JMI_MVM/MetaClassifier.py
JMI_MVM/__init__.py
JMI_MVM/__init__orig.py
JMI_MVM/functions.py
JMI_MVM/startup.py
JMI_MVM/files/CSSv2.css
JMI_MVM-0.3.4.dist-info/LICENSE
JMI_MVM-0.3.4.dist-info/METADATA
JMI_MVM-0.3.4.dist-info/WHEEL
JMI_MVM-0.3.4.dist-info/top_level.txt
JMI_MVM-0.3.4.dist-info/RECORD
