Metadata-Version: 2.1
Name: JMI-MVM
Version: 0.3.4
Summary: A collection of our functions and classes from bootcamp. 
Home-page: https://github.com/jirvingphd/JMI_MVM
Author: James M. Irving, Michael V. Moravetz
Author-email: james.irving.phd@outlook.com
License: UNKNOWN
Platform: UNKNOWN
Classifier: Programming Language :: Python :: 3
Classifier: License :: OSI Approved :: MIT License
Classifier: Operating System :: OS Independent
Requires-Dist: numpy
Requires-Dist: pandas
Requires-Dist: seaborn
Requires-Dist: matplotlib
Requires-Dist: sklearn
Requires-Dist: pydotplus
Requires-Dist: scipy
Requires-Dist: xgboost
